MANIFEST.in
README
setup.py
.hg/last-message.txt
docs/index.rst
docs/_build/html/changelog.html
docs/_build/html/features.html
docs/_build/html/genindex.html
docs/_build/html/index.html
docs/_build/html/jumbo.html
docs/_build/html/py-modindex.html
docs/_build/html/search.html
docs/_build/html/searchindex.js
docs/_build/html/_images/admin_tabs.png
docs/_build/html/_images/ajax_inlines.png
docs/_build/html/_modules/index.html
docs/_build/html/_modules/jmb/core/conf.html
docs/_build/html/_modules/jmb/core/monkey.html
docs/_build/html/_modules/jmb/core/admin/ajax_inlines.html
docs/_build/html/_modules/jmb/core/admin/dashboard.html
docs/_build/html/_modules/jmb/core/db/utils.html
docs/_build/html/_modules/jmb/core/middleware/thread_local.html
docs/_build/html/_modules/jmb/core/monkey/conf.html
docs/_build/html/_modules/jmb/core/utils/autocomplete.html
docs/_build/html/_modules/jmb/core/utils/data_import.html
docs/_build/html/_modules/jmb/core/utils/ics.html
docs/_build/html/_modules/jmb/core/views/generic/create_oo_file.html
docs/_build/html/_sources/changelog.txt
docs/_build/html/_sources/features.txt
docs/_build/html/_sources/index.txt
docs/_build/html/_sources/jumbo.txt
docs/_build/html/_sources/django/content.txt
docs/_build/html/_sources/django/addon/admin_actions.txt
docs/_build/html/_sources/django/addon/admin_tabs.txt
docs/_build/html/_sources/django/addon/ajax_inlines.txt
docs/_build/html/_sources/django/addon/content.txt
docs/_build/html/_sources/django/addon/search_form.txt
docs/_build/html/_sources/django/conf/conf.txt
docs/_build/html/_sources/django/conf/content.txt
docs/_build/html/_sources/django/conf/middleware.txt
docs/_build/html/_sources/django/conf/permessi.txt
docs/_build/html/_sources/django/javascript/content.txt
docs/_build/html/_sources/django/javascript/javascript.txt
docs/_build/html/_sources/django/javascript/picker.txt
docs/_build/html/_sources/django/javascript/popup.txt
docs/_build/html/_sources/django/misc/autocompletion.txt
jmb.core.egg-info/PKG-INFO
jmb.core.egg-info/SOURCES.txt
jmb.core.egg-info/dependency_links.txt
jmb.core.egg-info/namespace_packages.txt
jmb.core.egg-info/not-zip-safe
jmb.core.egg-info/requires.txt
jmb.core.egg-info/top_level.txt
