Metadata-Version: 1.1
Name: jmb.core
Version: 0.7
Summary: jumbo 2 core
Home-page: http://hg.thundersystems.it/jmb/jmb.core
Author: ThunderSystems
Author-email: dev@thundersystems.it
License: UNKNOWN
Platform: any
Classifier: Operating System :: OS Independent
Classifier: Programming Language :: Python
Classifier: Topic :: Internet :: WWW/HTTP :: Dynamic Content
Classifier: Framework :: Django
